[
  {
    "id": 1,
    "title": "وقفة مع آية الكرسي",
    "transcript": "",
    "author": "أ.د. حمود بن محسن الدعجاني",
    "audioUrl": "/audio/وقفة مع آية الكرسي قسم القرآن.mp3"
  },
  {
    "id": 2,
    "title": "شرح فضائل القرآن من صحيح البخاري 1",
    "transcript": "",
    "author": "أ.د. حمود بن محسن الدعجاني",
    "audioUrl": "/audio/شرح فضائل القرآن من صحيح البخاري 1.mp4"
  }
  ,
  {
    "id": 3,
    "title": "شرح فضائل القرآن من صحيح البخاري 2",
    "transcript": "",
    "author": "أ.د. حمود بن محسن الدعجاني",
    "audioUrl": "/audio/شرح فضائل القرآن من صحيح البخاري 2.mp4"
  },
  {
    "id": 4,
    "title": "شرح فضائل القرآن من صحيح البخاري 3",
    "transcript": "",
    "author": "أ.د. حمود بن محسن الدعجاني",
    "audioUrl": "/audio/شرح فضائل القرآن من صحيح البخاري 3.mp4"
  },
  {
    "id": 5,
    "title": "شرح فضائل القرآن من صحيح البخاري 4",
    "transcript": "",
    "author": "أ.د. حمود بن محسن الدعجاني",
    "audioUrl": "/audio/شرح فضائل القرآن من صحيح البخاري 4.mp4"
  },
  {
    "id": 6,
    "title": "شرح فضائل القرآن من صحيح البخاري 5",
    "transcript": "",
    "author": "أ.د. حمود بن محسن الدعجاني",
    "audioUrl": "/audio/شرح فضائل القرآن من صحيح البخاري 5.mp4"
  },
  {
    "id": 7,
    "title": "شرح فضائل القرآن من صحيح البخاري 6",
    "transcript": "",
    "author": "أ.د. حمود بن محسن الدعجاني",
    "audioUrl": "/audio/شرح فضائل القرآن من صحيح البخاري 6.mp4"
  },
  {
    "id": 8,
    "title": "شرح فضائل القرآن من صحيح البخاري 7",
    "transcript": "",
    "author": "أ.د. حمود بن محسن الدعجاني",
    "audioUrl": "/audio/شرح فضائل القرآن من صحيح البخاري 7.mp4"
  },
  {
    "id": 9,
    "title": "شرح فضائل القرآن من صحيح البخاري 8",
    "transcript": "",
    "author": "أ.د. حمود بن محسن الدعجاني",
    "audioUrl": "/audio/شرح فضائل القرآن من صحيح البخاري 8.mp4"
  },
  {
    "id": 10,
    "title": "شرح فضائل القرآن من صحيح البخاري 9",
    "transcript": "",
    "author": "أ.د. حمود بن محسن الدعجاني",
    "audioUrl": "/audio/شرح فضائل القرآن من صحيح البخاري 9.mp4"
  },
  {
    "id": 11,
    "title": "شرح فضائل القرآن من صحيح البخاري 10",
    "transcript": "",
    "author": "أ.د. حمود بن محسن الدعجاني",
    "audioUrl": "/audio/شرح فضائل القرآن من صحيح البخاري 10.mp4"
  },
  {
    "id": 12,
    "title": "شرح فضائل القرآن من صحيح البخاري 11",
    "transcript": "",
    "author": "أ.د. حمود بن محسن الدعجاني",
    "audioUrl": "/audio/شرح فضائل القرآن من صحيح البخاري 11.mp4"
  },
  {
    "id": 13,
    "title": "شرح فضائل القرآن من صحيح البخاري 12",
    "transcript": "",
    "author": "أ.د. حمود بن محسن الدعجاني",
    "audioUrl": "/audio/شرح فضائل القرآن من صحيح البخاري 12.mp4"
  },
  {
    "id": 14,
    "title": "شرح فضائل القرآن من صحيح البخاري 13",
    "transcript": "",
    "author": "أ.د. حمود بن محسن الدعجاني",
    "audioUrl": "/audio/شرح فضائل القرآن من صحيح البخاري 13.mp4"
  },
  {
    "id": 15,
    "title": "شرح فضائل القرآن من صحيح البخاري 14",
    "transcript": "",
    "author": "أ.د. حمود بن محسن الدعجاني",
    "audioUrl": "/audio/شرح فضائل القرآن من صحيح البخاري 14.mp4"
  },
  {
    "id": 16,
    "title": "شرح فضائل القرآن من صحيح البخاري 15",
    "transcript": "",
    "author": "أ.د. حمود بن محسن الدعجاني",
    "audioUrl": "/audio/شرح فضائل القرآن من صحيح البخاري 15.mp4"
  }
  
]



